{
  "kind": "collectionType",
  "collectionName": "materials",
  "info": {
    "singularName": "material",
    "pluralName": "materials",
    "displayName": "Material",
    "description": "Material complementar de uma aula"
  },
  "options": {
    "draftAndPublish": false
  },
  "attributes": {
    "name": {
      "type": "string",
      "required": true
    },
    "file": {
      "type": "media",
      "multiple": false,
      "required": true,
      "allowedTypes": ["files", "images", "videos", "audios"]
    },
    "lesson": {
      "type": "relation",
      "relation": "manyToOne",
      "target": "api::lesson.lesson",
      "inversedBy": "materials"
    }
  }
}
